./.env.example
./.gitignore
./CLAUDE.md
./LICENSE
./PKG-INFO
./README.md
./main.py
./pyproject.toml
./uv.lock
./tests/__init__.py
./tests/conftest.py
./tests/test_discord_mcp.py
./tests/test_error_handling.py
./tests/test_mcp_integration.py
wonderland_discord_mcp-0.1.1.dist-info/METADATA
wonderland_discord_mcp-0.1.1.dist-info/WHEEL
wonderland_discord_mcp-0.1.1.dist-info/entry_points.txt
wonderland_discord_mcp-0.1.1.dist-info/licenses/LICENSE
wonderland_discord_mcp-0.1.1.dist-info/RECORD
