Metadata-Version: 2.4
Name: wonderland-discord-mcp
Version: 0.1.1
Summary: Discord MCP Server - Model Context Protocol server for Discord API integration
Project-URL: Homepage, https://github.com/defi-wonderland/discord-mcp
Project-URL: Repository, https://github.com/defi-wonderland/discord-mcp
Project-URL: Issues, https://github.com/defi-wonderland/discord-mcp/issues
Author-email: Wonderland <security@wonderland.xyz>
License: MIT
License-File: LICENSE
Keywords: ai,chatbot,discord,mcp,model-context-protocol
Classifier: Development Status :: 4 - Beta
Classifier: Intended Audience :: Developers
Classifier: License :: OSI Approved :: MIT License
Classifier: Programming Language :: Python :: 3
Classifier: Programming Language :: Python :: 3.10
Classifier: Programming Language :: Python :: 3.11
Classifier: Programming Language :: Python :: 3.12
Classifier: Topic :: Communications :: Chat
Classifier: Topic :: Software Development :: Libraries :: Python Modules
Requires-Python: >=3.10
Requires-Dist: httpx>=0.28.1
Requires-Dist: mcp>=1.9.4
Requires-Dist: python-dotenv>=1.1.0
